[
  {
    "name": "setup",
    "path": "/home/droo/Downloads/nix-mox/scripts/core/setup.nu",
    "description": "nix-mox Unified Setup Script",
    "platform": "all",
    "requires_root": false,
    "dependencies": [],
    "category": "core",
    "executable": false,
    "size": 6652,
    "modified": "2025-07-24 19:33:07.928038814 +02:00"
  },
  {
    "name": "test-remote-builder",
    "path": "/home/droo/Downloads/nix-mox/scripts/core/test-remote-builder.nu",
    "description": "Test Remote Nix Builder Script",
    "platform": "all",
    "requires_root": false,
    "dependencies": [],
    "category": "core",
    "executable": false,
    "size": 6572,
    "modified": "2025-07-24 19:33:07.929038849 +02:00"
  },
  {
    "name": "setup-cachix",
    "path": "/home/droo/Downloads/nix-mox/scripts/core/setup-cachix.nu",
    "description": "Setup script for Cachix credentials",
    "platform": "all",
    "requires_root": false,
    "dependencies": [],
    "category": "core",
    "executable": false,
    "size": 2158,
    "modified": "2025-07-24 19:33:07.927038778 +02:00"
  },
  {
    "name": "install",
    "path": "/home/droo/Downloads/nix-mox/scripts/core/install.nu",
    "description": "Simplified install script for nix-mox",
    "platform": "all",
    "requires_root": false,
    "dependencies": [],
    "category": "core",
    "executable": false,
    "size": 8704,
    "modified": "2025-07-24 19:33:07.926038742 +02:00"
  },
  {
    "name": "health-check",
    "path": "/home/droo/Downloads/nix-mox/scripts/core/health-check.nu",
    "description": "nix-mox Health Check Script",
    "platform": "all",
    "requires_root": false,
    "dependencies": [],
    "category": "core",
    "executable": false,
    "size": 16207,
    "modified": "2025-07-24 19:33:07.924038671 +02:00"
  },
  {
    "name": "setup-remote-builder",
    "path": "/home/droo/Downloads/nix-mox/scripts/core/setup-remote-builder.nu",
    "description": "Remote Nix Builder Setup Script",
    "platform": "all",
    "requires_root": false,
    "dependencies": [],
    "category": "core",
    "executable": false,
    "size": 7559,
    "modified": "2025-07-24 19:33:07.928038814 +02:00"
  },
  {
    "name": "integrate-modules",
    "path": "/home/droo/Downloads/nix-mox/scripts/core/integrate-modules.nu",
    "description": "nix-mox Module Integration Script",
    "platform": "all",
    "requires_root": false,
    "dependencies": [],
    "category": "core",
    "executable": false,
    "size": 5446,
    "modified": "2025-07-24 19:33:07.927038778 +02:00"
  },
  {
    "name": "cleanup",
    "path": "/home/droo/Downloads/nix-mox/scripts/core/cleanup.nu",
    "description": "nix-mox Cleanup Script",
    "platform": "all",
    "requires_root": false,
    "dependencies": [],
    "category": "core",
    "executable": false,
    "size": 3918,
    "modified": "2025-07-24 19:33:07.922038600 +02:00"
  },
  {
    "name": "setup-remote-builder",
    "path": "/home/droo/Downloads/nix-mox/scripts/core/setup-remote-builder.sh",
    "description": "Remote Nix Builder Setup Script",
    "platform": "all",
    "requires_root": false,
    "dependencies": [],
    "category": "core",
    "executable": false,
    "size": 7622,
    "modified": "2025-07-24 19:33:07.915970626 +02:00"
  },
  {
    "name": "summarize-tests",
    "path": "/home/droo/Downloads/nix-mox/scripts/core/summarize-tests.sh",
    "description": "Summarize test failures from a Nushell test run.",
    "platform": "all",
    "requires_root": false,
    "dependencies": [],
    "category": "core",
    "executable": false,
    "size": 5803,
    "modified": "2025-07-24 19:33:07.916953712 +02:00"
  },
  {
    "name": "test-remote-builder",
    "path": "/home/droo/Downloads/nix-mox/scripts/core/test-remote-builder.sh",
    "description": "Test Remote Nix Builder Script",
    "platform": "all",
    "requires_root": false,
    "dependencies": [],
    "category": "core",
    "executable": false,
    "size": 6475,
    "modified": "2025-07-24 19:33:07.918775800 +02:00"
  },
  {
    "name": "test-ci-local",
    "path": "/home/droo/Downloads/nix-mox/scripts/core/test-ci-local.sh",
    "description": "Local CI Testing Script for nix-mox",
    "platform": "all",
    "requires_root": false,
    "dependencies": [],
    "category": "core",
    "executable": false,
    "size": 7192,
    "modified": "2025-07-24 19:33:07.917794519 +02:00"
  },
  {
    "name": "ci-test",
    "path": "/home/droo/Downloads/nix-mox/scripts/core/ci-test.sh",
    "description": "Simple CI Testing Script for nix-mox",
    "platform": "all",
    "requires_root": false,
    "dependencies": [],
    "category": "core",
    "executable": false,
    "size": 2875,
    "modified": "2025-07-24 19:33:07.915056391 +02:00"
  },
  {
    "name": "generate-coverage",
    "path": "/home/droo/Downloads/nix-mox/scripts/tools/generate-coverage.nu",
    "description": "Unified Coverage Report Generator",
    "platform": "all",
    "requires_root": false,
    "dependencies": [],
    "category": "tools",
    "executable": false,
    "size": 11372,
    "modified": "2025-07-24 21:15:06.814543409 +02:00"
  },
  {
    "name": "project-dashboard",
    "path": "/home/droo/Downloads/nix-mox/scripts/tools/project-dashboard.nu",
    "description": "nix-mox Project Status Dashboard",
    "platform": "all",
    "requires_root": false,
    "dependencies": [],
    "category": "tools",
    "executable": false,
    "size": 6604,
    "modified": "2025-07-24 19:33:07.972040381 +02:00"
  },
  {
    "name": "analyze-sizes",
    "path": "/home/droo/Downloads/nix-mox/scripts/tools/analyze-sizes.nu",
    "description": "nix-mox Size Analysis Script",
    "platform": "all",
    "requires_root": false,
    "dependencies": [],
    "category": "tools",
    "executable": false,
    "size": 15681,
    "modified": "2025-07-24 21:22:20.650704178 +02:00"
  },
  {
    "name": "generate-docs",
    "path": "/home/droo/Downloads/nix-mox/scripts/tools/generate-docs.nu",
    "description": "Documentation generation tool for nix-mox scripts",
    "platform": "all",
    "requires_root": false,
    "dependencies": [],
    "category": "tools",
    "executable": false,
    "size": 15514,
    "modified": "2025-07-24 22:40:45.595350835 +02:00"
  },
  {
    "name": "generate-sbom",
    "path": "/home/droo/Downloads/nix-mox/scripts/tools/generate-sbom.nu",
    "description": "nix-mox SBOM Generator",
    "platform": "all",
    "requires_root": false,
    "dependencies": [],
    "category": "tools",
    "executable": false,
    "size": 9038,
    "modified": "2025-07-24 22:09:13.238593445 +02:00"
  },
  {
    "name": "size-dashboard",
    "path": "/home/droo/Downloads/nix-mox/scripts/tools/size-dashboard.nu",
    "description": "nix-mox Size Analysis Dashboard",
    "platform": "all",
    "requires_root": false,
    "dependencies": [],
    "category": "tools",
    "executable": false,
    "size": 13885,
    "modified": "2025-07-24 19:33:07.973040416 +02:00"
  },
  {
    "name": "advanced-cache",
    "path": "/home/droo/Downloads/nix-mox/scripts/tools/advanced-cache.nu",
    "description": "nix-mox Advanced Caching Strategy",
    "platform": "all",
    "requires_root": false,
    "dependencies": [],
    "category": "tools",
    "executable": false,
    "size": 10295,
    "modified": "2025-07-24 21:24:24.717794961 +02:00"
  },
  {
    "name": "cleanup",
    "path": "/home/droo/Downloads/nix-mox/scripts/tools/cleanup.nu",
    "description": "nix-mox Cleanup Script",
    "platform": "all",
    "requires_root": false,
    "dependencies": [],
    "category": "tools",
    "executable": false,
    "size": 6483,
    "modified": "2025-07-24 21:07:15.175992779 +02:00"
  },
  {
    "name": "analyze-sizes",
    "path": "/home/droo/Downloads/nix-mox/scripts/tools/analyze-sizes.sh",
    "description": "nix-mox Size Analysis Script",
    "platform": "all",
    "requires_root": false,
    "dependencies": [],
    "category": "tools",
    "executable": false,
    "size": 10823,
    "modified": "2025-07-24 19:33:07.921835116 +02:00"
  },
  {
    "name": "uninstall",
    "path": "/home/droo/Downloads/nix-mox/scripts/linux/uninstall.nu",
    "description": "uninstall.nu - Remove nix-mox scripts installed by install.nu",
    "platform": "linux",
    "requires_root": false,
    "dependencies": [],
    "category": "general",
    "executable": false,
    "size": 2101,
    "modified": "2025-07-24 19:33:07.948039526 +02:00"
  },
  {
    "name": "nixos-flake-update",
    "path": "/home/droo/Downloads/nix-mox/scripts/linux/nixos-flake-update.nu",
    "description": "NixOS Flake Update & Rebuild Script",
    "platform": "linux",
    "requires_root": false,
    "dependencies": [],
    "category": "general",
    "executable": false,
    "size": 2513,
    "modified": "2025-07-24 19:33:07.947039490 +02:00"
  },
  {
    "name": "vzdump-backup",
    "path": "/home/droo/Downloads/nix-mox/scripts/linux/vzdump-backup.nu",
    "description": "vzdump-backup.nu - Backup Proxmox VMs using vzdump",
    "platform": "linux",
    "requires_root": false,
    "dependencies": [],
    "category": "general",
    "executable": false,
    "size": 2060,
    "modified": "2025-07-24 19:33:07.948039526 +02:00"
  },
  {
    "name": "setup-interactive",
    "path": "/home/droo/Downloads/nix-mox/scripts/linux/setup-interactive.nu",
    "description": "No description available",
    "platform": "linux",
    "requires_root": false,
    "dependencies": [],
    "category": "general",
    "executable": false,
    "size": 2,
    "modified": "2025-07-24 19:33:07.947039490 +02:00"
  },
  {
    "name": "proxmox-update",
    "path": "/home/droo/Downloads/nix-mox/scripts/linux/proxmox-update.nu",
    "description": "proxmox-update.nu - Update Proxmox VE",
    "platform": "linux",
    "requires_root": false,
    "dependencies": [],
    "category": "general",
    "executable": false,
    "size": 2890,
    "modified": "2025-07-24 19:33:07.947039490 +02:00"
  },
  {
    "name": "install",
    "path": "/home/droo/Downloads/nix-mox/scripts/linux/install.nu",
    "description": "install.nu - Install nix-mox scripts",
    "platform": "linux",
    "requires_root": false,
    "dependencies": [],
    "category": "general",
    "executable": false,
    "size": 3983,
    "modified": "2025-07-24 19:33:07.947039490 +02:00"
  },
  {
    "name": "zfs-snapshot",
    "path": "/home/droo/Downloads/nix-mox/scripts/linux/zfs-snapshot.nu",
    "description": "ZFS Snapshot & Prune Script",
    "platform": "linux",
    "requires_root": false,
    "dependencies": [],
    "category": "general",
    "executable": false,
    "size": 3547,
    "modified": "2025-07-24 19:33:07.949039561 +02:00"
  },
  {
    "name": "_common",
    "path": "/home/droo/Downloads/nix-mox/scripts/linux/_common.sh",
    "description": "Common functions for nix-mox Linux scripts (Bash)",
    "platform": "linux",
    "requires_root": false,
    "dependencies": [],
    "category": "general",
    "executable": false,
    "size": 1429,
    "modified": "2025-07-24 19:33:07.919601616 +02:00"
  },
  {
    "name": "install-steam-rust",
    "path": "/home/droo/Downloads/nix-mox/scripts/windows/install-steam-rust.nu",
    "description": "install-steam-rust.nu",
    "platform": "windows",
    "requires_root": false,
    "dependencies": [],
    "category": "general",
    "executable": false,
    "size": 3421,
    "modified": "2025-07-24 19:33:07.973040416 +02:00"
  },
  {
    "name": "run-steam-rust",
    "path": "/home/droo/Downloads/nix-mox/scripts/windows/run-steam-rust.bat",
    "description": "No description available",
    "platform": "windows",
    "requires_root": false,
    "dependencies": [],
    "category": "general",
    "executable": false,
    "size": 1239,
    "modified": "2025-06-20 17:03:02.636504920 +02:00"
  },
  {
    "name": "install",
    "path": "/home/droo/Downloads/nix-mox/scripts/windows/install.ps1",
    "description": "nix-mox Windows Installation Script",
    "platform": "windows",
    "requires_root": false,
    "dependencies": [],
    "category": "general",
    "executable": false,
    "size": 1235,
    "modified": "2025-07-02 22:28:16.237339499 +02:00"
  },
  {
    "name": "uninstall",
    "path": "/home/droo/Downloads/nix-mox/scripts/windows/uninstall.ps1",
    "description": "nix-mox Windows Uninstallation Script",
    "platform": "windows",
    "requires_root": false,
    "dependencies": [],
    "category": "general",
    "executable": false,
    "size": 1130,
    "modified": "2025-07-02 22:28:16.237339499 +02:00"
  },
  {
    "name": "get-config",
    "path": "/home/droo/Downloads/nix-mox/scripts/windows/get-config.ps1",
    "description": "No description available",
    "platform": "windows",
    "requires_root": false,
    "dependencies": [],
    "category": "general",
    "executable": false,
    "size": 126,
    "modified": "2025-07-02 22:28:16.237339499 +02:00"
  },
  {
    "name": "nix-mox",
    "path": "/home/droo/Downloads/nix-mox/scripts/common/nix-mox.nu",
    "description": "Main script for nix-mox",
    "platform": "all",
    "requires_root": false,
    "dependencies": [],
    "category": "general",
    "executable": false,
    "size": 9353,
    "modified": "2025-07-24 19:33:07.922038600 +02:00"
  },
  {
    "name": "nix-mox-uninstall",
    "path": "/home/droo/Downloads/nix-mox/scripts/common/nix-mox-uninstall.sh",
    "description": "Default values",
    "platform": "all",
    "requires_root": false,
    "dependencies": [],
    "category": "general",
    "executable": false,
    "size": 1469,
    "modified": "2025-07-24 19:33:07.914166730 +02:00"
  },
  {
    "name": "install-nix",
    "path": "/home/droo/Downloads/nix-mox/scripts/common/install-nix.sh",
    "description": "This script installs the Nix package manager on your system by",
    "platform": "all",
    "requires_root": false,
    "dependencies": [],
    "category": "general",
    "executable": false,
    "size": 3982,
    "modified": "2025-07-24 19:33:07.913375883 +02:00"
  },
  {
    "name": "setup-hydepwns-dotfiles",
    "path": "/home/droo/Downloads/nix-mox/scripts/setup-hydepwns-dotfiles.sh",
    "description": "Setup script for Hydepwns dotfiles integration",
    "platform": "all",
    "requires_root": false,
    "dependencies": [],
    "category": "general",
    "executable": false,
    "size": 2203,
    "modified": "2025-07-24 19:33:07.920427367 +02:00"
  }
]